[{"x":3.39,"y":0},"3"],
[{"x":10.97,"y":-1},"8"],
[{"x":2.26,"y":-0.85},"2"],
[{"x":4.53,"y":-1},"4"],
[{"x":5.66,"y":-1},"5"],
[{"x":12.11,"y":-1},"9"],
[{"x":9.84,"y":-1},"7"],
[{"x":8.71,"y":-1},"6"],
[{"x":0,"y":-0.89},"undefined"],
[{"x":14.37,"y":-1},"undefined"],
[{"x":1.13,"y":-0.95},"1"],
[{"x":13.24,"y":-1},"0"],
[{"x":3.39,"y":-0.23},"e"],
[{"x":10.97,"y":-1},"i"],
[{"x":2.26,"y":-0.85},"w"],
[{"x":4.53,"y":-1},"r"],
[{"x":5.66,"y":-1},"t"],
[{"x":12.11,"y":-1},"o"],
[{"x":9.84,"y":-1},"u"],
[{"x":8.71,"y":-1},"y"],
[{"x":0,"y":-0.89},"undefined"],
[{"x":14.37,"y":-1},"undefined"],
[{"x":1.13,"y":-0.95},"q"],
[{"x":13.24,"y":-1},"p"],
[{"x":3.39,"y":-0.23},"d"],
[{"x":10.97,"y":-1},"k"],
[{"x":2.26,"y":-0.85},"s"],
[{"x":4.53,"y":-1},"f"],
[{"x":5.66,"y":-1},"g"],
[{"x":12.11,"y":-1},"l"],
[{"x":9.84,"y":-1},"j"],
[{"x":8.71,"y":-1},"h"],
[{"x":0,"y":-0.9},"undefined"],
[{"x":14.37,"y":-1},"undefined"],
[{"x":1.13,"y":-0.94},"a"],
[{"x":13.24,"y":-1},";"],
[{"x":3.39,"y":-0.23},"c"],
[{"x":10.97,"y":-1},","],
[{"x":2.26,"y":-0.85},"x"],
[{"x":4.53,"y":-1},"v"],
[{"x":5.66,"y":-1},"b"],
[{"x":12.11,"y":-1},"."],
[{"x":9.84,"y":-1},"m"],
[{"x":8.71,"y":-1},"n"],
[{"x":0,"y":-0.9},"undefined"],
[{"x":14.37,"y":-1},"undefined"],
[{"x":1.13,"y":-0.94},"z"],
[{"x":13.24,"y":-1},"/"],
[{"x":3.39,"y":-0.23},"undefined"],
[{"x":10.97,"y":-1},"undefined"],
[{"x":2.26,"y":-0.85},"undefined"],
[{"x":4.53,"y":-1},"undefined"],
[{"x":5.66,"y":-1},"undefined"],
[{"x":12.11,"y":-1},"undefined"],
[{"x":9.84,"y":-1},"undefined"],
[{"x":8.71,"y":-1},"undefined"]